inte_reports/__init__.py
inte_reports/ae_report.py
inte_reports/apps.py
inte_reports/death_report.py
inte_reports/models.py
inte_reports/pdf_report.py
inte_reports/migrations/__init__.py
inte_reports/tests/__init__.py
inte_reports/tests/test_reports.py
inte_reports/tests/urls.py
inte_reports-0.1.2.dist-info/LICENSE
inte_reports-0.1.2.dist-info/METADATA
inte_reports-0.1.2.dist-info/WHEEL
inte_reports-0.1.2.dist-info/top_level.txt
inte_reports-0.1.2.dist-info/RECORD
